test_gpu.py
packages/test_gpu.py
hf_gpu_test-1.0.0.0.dist-info/METADATA
hf_gpu_test-1.0.0.0.dist-info/WHEEL
hf_gpu_test-1.0.0.0.dist-info/top_level.txt
hf_gpu_test-1.0.0.0.dist-info/RECORD
