Metadata-Version: 2.1
Name: hf-gpu-test
Version: 1.0.0.0
Summary: Huggingface GPU Test Package
Home-page: 
Author: appleeji
Author-email: appleeji@naver.com
License: MIT
Requires-Python: >=3
Requires-Dist: torch
Requires-Dist: transformers
